piconard/__init__.py
piconard/main.py
piconard-0.0.3.dist-info/entry_points.txt
piconard-0.0.3.dist-info/WHEEL
piconard-0.0.3.dist-info/METADATA
piconard-0.0.3.dist-info/RECORD
